{
    "estadisticas": {
        "total_canciones": 1,
        "total_artistas": 3,
        "total_albumes": 1,
        "me_gusta": 0,
        "favorito": 0
    },
    "canciones": [
        {
            "ruta": "C:\\Users\\Victor\\Music\\pm\\530.mp3",
            "titulo": "530",
            "artista": "¥$ ft Kanye West, Ty Dolla $ign",
            "artista_album": "¥$ ft Kanye West, Ty Dolla $ign",
            "album": "VULTURES 2",
            "duracion": 289.5412244897959,
            "duracion_formateada": "04:49",
            "anio": "2024-08-03",
            "numero_pista": "7/16",
            "tiene_caratula": true,
            "me_gusta": false,
            "favorito": false
        }
    ]
}